MANIFEST.in
README.md
build_catalog_enviroment.py
setup.py
setup.sh
CC_CataLog.egg-info/PKG-INFO
CC_CataLog.egg-info/SOURCES.txt
CC_CataLog.egg-info/dependency_links.txt
CC_CataLog.egg-info/entry_points.txt
CC_CataLog.egg-info/requires.txt
CC_CataLog.egg-info/top_level.txt
catalog/__init__.py
catalog/catalog_config.py
catalog/cli/__init__.py
catalog/cli/gui.py
catalog/cli/main.py
catalog/data/__init__.py
catalog/data/data_sol53_54_57_58_bm32_se30.py
catalog/data/data_solids.py
catalog/data/data_solids_wPBE.py
catalog/data/emt.py
catalog/datalog/__init__.py
catalog/datalog/datalog.py
catalog/datalog/db_utils.py
catalog/datalog/manageDB.py
catalog/datalog/syncing.py
catalog/fw/__init__.py
catalog/fw/incomplete.py
catalog/fw/launcher.py
catalog/fw/launcher.sh
catalog/fw/qadapter_templates/LoadSharingFacility_template.txt
catalog/fw/qadapter_templates/PBS_template.txt
catalog/fw/qadapter_templates/SLURM_template.txt
catalog/gendata/__init__.py
catalog/gendata/gendata.py
catalog/gendata/interstitialFuncs.py
catalog/gendata/surfFuncs.py
catalog/gendata/traj_to_job.py
catalog/gui/__init__.py
catalog/gui/gendata_form.py
catalog/gui/job_maker.py
catalog/gui/launch_form.py
catalog/gui/main.py
catalog/gui/plotly-latest.min.js
catalog/gui/plotly_viewer.py
catalog/gui/relauncher.py
catalog/jobs/__init__.py
catalog/jobs/cluster.py
catalog/jobs/jobs.py
catalog/jobs/repeat.py
catalog/jobs/scripts.py
catalog/jobs/version_utils.py
catalog/jobs/versions.py
catalog/misc/__init__.py
catalog/misc/atoms.py
catalog/misc/plotly_atoms.py
catalog/misc/print_parse.py
catalog/misc/sql_utils.py
catalog/misc/ssh_utils.py
catalog/misc/utilities.py